hntpy/__init__.py
hntpy/helium_client.py
hntpy/network/__init__.py
hntpy/network/oracle.py
hntpy/network/stats.py
hntpy/resources/__init__.py
hntpy/resources/account.py
hntpy/resources/base.py
hntpy/resources/hotspot.py
hntpy/resources/validator.py
hntpy-0.0.9.dist-info/entry_points.txt
hntpy-0.0.9.dist-info/LICENSE
hntpy-0.0.9.dist-info/WHEEL
hntpy-0.0.9.dist-info/METADATA
hntpy-0.0.9.dist-info/RECORD
